{
  "question_name": "maximum-number-of-vowels-in-a-substring-of-given-length",
  "problem_metadata": {
    "questionId": "1567",
    "title": "Maximum Number of Vowels in a Substring of Given Length",
    "titleSlug": "maximum-number-of-vowels-in-a-substring-of-given-length",
    "content": "<p>Given a string <code>s</code> and an integer <code>k</code>, return <em>the maximum number of vowel letters in any substring of </em><code>s</code><em> with length </em><code>k</code>.</p>\n\n<p><strong>Vowel letters</strong> in English are <code>&#39;a&#39;</code>, <code>&#39;e&#39;</code>, <code>&#39;i&#39;</code>, <code>&#39;o&#39;</code>, and <code>&#39;u&#39;</code>.</p>\n\n<p>&nbsp;</p>\n<p><strong class=\"example\">Example 1:</strong></p>\n\n<pre>\n<strong>Input:</strong> s = &quot;abciiidef&quot;, k = 3\n<strong>Output:</strong> 3\n<strong>Explanation:</strong> The substring &quot;iii&quot; contains 3 vowel letters.\n</pre>\n\n<p><strong class=\"example\">Example 2:</strong></p>\n\n<pre>\n<strong>Input:</strong> s = &quot;aeiou&quot;, k = 2\n<strong>Output:</strong> 2\n<strong>Explanation:</strong> Any substring of length 2 contains 2 vowels.\n</pre>\n\n<p><strong class=\"example\">Example 3:</strong></p>\n\n<pre>\n<strong>Input:</strong> s = &quot;leetcode&quot;, k = 3\n<strong>Output:</strong> 2\n<strong>Explanation:</strong> &quot;lee&quot;, &quot;eet&quot; and &quot;ode&quot; contain 2 vowels.\n</pre>\n\n<p>&nbsp;</p>\n<p><strong>Constraints:</strong></p>\n\n<ul>\n\t<li><code>1 &lt;= s.length &lt;= 10<sup>5</sup></code></li>\n\t<li><code>s</code> consists of lowercase English letters.</li>\n\t<li><code>1 &lt;= k &lt;= s.length</code></li>\n</ul>\n",
    "difficulty": "Medium",
    "stats": "{\"totalAccepted\": \"647.3K\", \"totalSubmission\": \"1.1M\", \"totalAcceptedRaw\": 647345, \"totalSubmissionRaw\": 1053964, \"acRate\": \"61.4%\"}",
    "topicTags": [
      {
        "name": "String",
        "slug": "string",
        "translatedName": null
      },
      {
        "name": "Sliding Window",
        "slug": "sliding-window",
        "translatedName": null
      }
    ],
    "hints": [
      "Keep a window of size k and maintain the number of vowels in it.",
      "Keep moving the window and update the number of vowels while moving. Answer is max number of vowels of any window."
    ]
  },
  "submissions": [
    {
      "id": "1833233135",
      "statusDisplay": "Accepted",
      "lang": {
        "name": "python3",
        "verboseName": "Python3"
      },
      "runtime": 469,
      "memory": 19028000,
      "timestamp": 1763463315,
      "title": "Maximum Number of Vowels in a Substring of Given Length",
      "titleSlug": "maximum-number-of-vowels-in-a-substring-of-given-length",
      "runtimeDisplay": "469 ms",
      "runtimePercentile": 5.0002999999999735,
      "memoryDisplay": "19 MB",
      "memoryPercentile": 51.858599999999996,
      "code": "class Solution:\n    def maxVowels(self, s: str, k: int) -> int:\n        vowels = set(['a','e','i','o','u'])\n        window = []\n        maxcount = 0\n        count = 0\n        for right in range(len(s)):\n            if s[right] in vowels:\n                count += 1\n            window.append(s[right])\n            if len(window) > k:\n                removed = window.pop(0)\n                if removed in vowels:\n                    count -= 1\n            if len(window) == k:\n                maxcount = max(maxcount,count)            \n        return maxcount",
      "statusCode": 10,
      "user": {
        "username": "saachinnnnn",
        "profile": {
          "realName": "Iam4ari"
        }
      },
      "question": {
        "questionId": "1567",
        "titleSlug": "maximum-number-of-vowels-in-a-substring-of-given-length",
        "hasFrontendPreview": false
      },
      "notes": "",
      "flagType": "WHITE",
      "topicTags": [],
      "runtimeError": null,
      "compileError": null
    },
    {
      "id": "1833220495",
      "statusDisplay": "Wrong Answer",
      "lang": {
        "name": "python3",
        "verboseName": "Python3"
      },
      "runtime": 71,
      "memory": 18700000,
      "timestamp": 1763462192,
      "title": "Maximum Number of Vowels in a Substring of Given Length",
      "titleSlug": "maximum-number-of-vowels-in-a-substring-of-given-length",
      "runtimeDisplay": "N/A",
      "runtimePercentile": null,
      "memoryDisplay": "N/A",
      "memoryPercentile": null,
      "code": "class Solution:\n    def maxVowels(self, s: str, k: int) -> int:\n        vowels = set(['a','e','i','o','u'])\n        window = []\n        count = 0\n        for right in range(len(s)):\n            if s[right] in vowels:\n                window.append(s[right])\n            else:\n                count = max(len(window),count)\n                window.clear()\n        return count ",
      "statusCode": 11,
      "user": {
        "username": "saachinnnnn",
        "profile": {
          "realName": "Iam4ari"
        }
      },
      "question": {
        "questionId": "1567",
        "titleSlug": "maximum-number-of-vowels-in-a-substring-of-given-length",
        "hasFrontendPreview": false
      },
      "notes": "",
      "flagType": "WHITE",
      "topicTags": [],
      "runtimeError": null,
      "compileError": null
    }
  ]
}