{
  "question_name": "number-of-students-unable-to-eat-lunch",
  "problem_metadata": {
    "questionId": "1802",
    "title": "Number of Students Unable to Eat Lunch",
    "titleSlug": "number-of-students-unable-to-eat-lunch",
    "content": "<p>The school cafeteria offers circular and square sandwiches at lunch break, referred to by numbers <code>0</code> and <code>1</code> respectively. All students stand in a queue. Each student either prefers square or circular sandwiches.</p>\n\n<p>The number of sandwiches in the cafeteria is equal to the number of students. The sandwiches are placed in a <strong>stack</strong>. At each step:</p>\n\n<ul>\n\t<li>If the student at the front of the queue <strong>prefers</strong> the sandwich on the top of the stack, they will <strong>take it</strong> and leave the queue.</li>\n\t<li>Otherwise, they will <strong>leave it</strong> and go to the queue&#39;s end.</li>\n</ul>\n\n<p>This continues until none of the queue students want to take the top sandwich and are thus unable to eat.</p>\n\n<p>You are given two integer arrays <code>students</code> and <code>sandwiches</code> where <code>sandwiches[i]</code> is the type of the <code>i<sup>​​​​​​th</sup></code> sandwich in the stack (<code>i = 0</code> is the top of the stack) and <code>students[j]</code> is the preference of the <code>j<sup>​​​​​​th</sup></code> student in the initial queue (<code>j = 0</code> is the front of the queue). Return <em>the number of students that are unable to eat.</em></p>\n\n<p>&nbsp;</p>\n<p><strong class=\"example\">Example 1:</strong></p>\n\n<pre>\n<strong>Input:</strong> students = [1,1,0,0], sandwiches = [0,1,0,1]\n<strong>Output:</strong> 0<strong> \nExplanation:</strong>\n- Front student leaves the top sandwich and returns to the end of the line making students = [1,0,0,1].\n- Front student leaves the top sandwich and returns to the end of the line making students = [0,0,1,1].\n- Front student takes the top sandwich and leaves the line making students = [0,1,1] and sandwiches = [1,0,1].\n- Front student leaves the top sandwich and returns to the end of the line making students = [1,1,0].\n- Front student takes the top sandwich and leaves the line making students = [1,0] and sandwiches = [0,1].\n- Front student leaves the top sandwich and returns to the end of the line making students = [0,1].\n- Front student takes the top sandwich and leaves the line making students = [1] and sandwiches = [1].\n- Front student takes the top sandwich and leaves the line making students = [] and sandwiches = [].\nHence all students are able to eat.\n</pre>\n\n<p><strong class=\"example\">Example 2:</strong></p>\n\n<pre>\n<strong>Input:</strong> students = [1,1,1,0,0,1], sandwiches = [1,0,0,0,1,1]\n<strong>Output:</strong> 3\n</pre>\n\n<p>&nbsp;</p>\n<p><strong>Constraints:</strong></p>\n\n<ul>\n\t<li><code>1 &lt;= students.length, sandwiches.length &lt;= 100</code></li>\n\t<li><code>students.length == sandwiches.length</code></li>\n\t<li><code>sandwiches[i]</code> is <code>0</code> or <code>1</code>.</li>\n\t<li><code>students[i]</code> is <code>0</code> or <code>1</code>.</li>\n</ul>\n",
    "difficulty": "Easy",
    "stats": "{\"totalAccepted\": \"357.6K\", \"totalSubmission\": \"450.6K\", \"totalAcceptedRaw\": 357594, \"totalSubmissionRaw\": 450639, \"acRate\": \"79.4%\"}",
    "topicTags": [
      {
        "name": "Array",
        "slug": "array",
        "translatedName": null
      },
      {
        "name": "Stack",
        "slug": "stack",
        "translatedName": null
      },
      {
        "name": "Queue",
        "slug": "queue",
        "translatedName": null
      },
      {
        "name": "Simulation",
        "slug": "simulation",
        "translatedName": null
      }
    ],
    "hints": [
      "Simulate the given in the statement",
      "Calculate those who will eat instead of those who will not."
    ]
  },
  "submissions": [
    {
      "id": "1834198058",
      "statusDisplay": "Accepted",
      "lang": {
        "name": "python3",
        "verboseName": "Python3"
      },
      "runtime": 0,
      "memory": 18052000,
      "timestamp": 1763555144,
      "title": "Number of Students Unable to Eat Lunch",
      "titleSlug": "number-of-students-unable-to-eat-lunch",
      "runtimeDisplay": "0 ms",
      "runtimePercentile": 100.0,
      "memoryDisplay": "18.1 MB",
      "memoryPercentile": 79.972,
      "code": "from collections import deque\nclass Solution:\n    def countStudents(self, students: List[int], sandwiches: List[int]) -> int:\n        if not students or not sandwiches:\n            return 0\n        \n        q1 : list = deque(students)\n        q2 : list = deque(sandwiches)\n        count : int = 0\n        while q1:\n            if q1[0] == q2[0]:\n                q1.popleft()\n                q2.popleft()\n                count = 0\n            else:\n                q1.append(q1.popleft())\n                count += 1\n            if count == len(q1):\n                break\n        return len(q1)",
      "statusCode": 10,
      "user": {
        "username": "saachinnnnn",
        "profile": {
          "realName": "Iam4ari"
        }
      },
      "question": {
        "questionId": "1802",
        "titleSlug": "number-of-students-unable-to-eat-lunch",
        "hasFrontendPreview": false
      },
      "notes": "",
      "flagType": "WHITE",
      "topicTags": [],
      "runtimeError": null,
      "compileError": null
    },
    {
      "id": "1817919340",
      "statusDisplay": "Accepted",
      "lang": {
        "name": "python3",
        "verboseName": "Python3"
      },
      "runtime": 0,
      "memory": 17684000,
      "timestamp": 1762019827,
      "title": "Number of Students Unable to Eat Lunch",
      "titleSlug": "number-of-students-unable-to-eat-lunch",
      "runtimeDisplay": "0 ms",
      "runtimePercentile": 100.0,
      "memoryDisplay": "17.7 MB",
      "memoryPercentile": 80.0949,
      "code": "from collections import deque\nclass Solution:\n    def countStudents(self, students: List[int], sandwiches: List[int]) -> int:\n        if not students or not sandwiches:\n            return 0\n        \n        q1 : list = deque(students)\n        q2 : list = deque(sandwiches)\n        count : int = 0\n        while q1:\n            if q1[0] == q2[0]:\n                q1.popleft()\n                q2.popleft()\n                count = 0\n            else:\n                q1.append(q1.popleft())\n                count += 1\n            if count == len(q1):\n                break\n        return len(q1)",
      "statusCode": 10,
      "user": {
        "username": "saachinnnnn",
        "profile": {
          "realName": "Iam4ari"
        }
      },
      "question": {
        "questionId": "1802",
        "titleSlug": "number-of-students-unable-to-eat-lunch",
        "hasFrontendPreview": false
      },
      "notes": "",
      "flagType": "WHITE",
      "topicTags": [],
      "runtimeError": null,
      "compileError": null
    },
    {
      "id": "1817914610",
      "statusDisplay": "Wrong Answer",
      "lang": {
        "name": "python3",
        "verboseName": "Python3"
      },
      "runtime": 5,
      "memory": 18012000,
      "timestamp": 1762019521,
      "title": "Number of Students Unable to Eat Lunch",
      "titleSlug": "number-of-students-unable-to-eat-lunch",
      "runtimeDisplay": "N/A",
      "runtimePercentile": null,
      "memoryDisplay": "N/A",
      "memoryPercentile": null,
      "code": "from collections import deque\nclass Solution:\n    def countStudents(self, students: List[int], sandwiches: List[int]) -> int:\n        if not students or not sandwiches:\n            return 0\n        \n        q1 : list = deque(students)\n        q2 : list = deque(sandwiches)\n        idx : int = 0\n        while idx < len(students) and not(0 in sandwiches and 0 not in students) and not(1 in sandwiches and 1 not in students):\n            if students[idx] == sandwiches[idx]:\n                students[idx] = sandwiches[idx] = -1\n                idx += 1\n            else:\n                students.append(students.pop(idx))\n        return sum(0 if sandwich == -1 else 1 for sandwich in sandwiches)",
      "statusCode": 11,
      "user": {
        "username": "saachinnnnn",
        "profile": {
          "realName": "Iam4ari"
        }
      },
      "question": {
        "questionId": "1802",
        "titleSlug": "number-of-students-unable-to-eat-lunch",
        "hasFrontendPreview": false
      },
      "notes": "",
      "flagType": "WHITE",
      "topicTags": [],
      "runtimeError": null,
      "compileError": null
    }
  ]
}